flask_lambda.py
flask_lambda/__init__.py
flask_lambda/util/__init__.py
flask_lambda/util/object_utils.py
flask_lambda_support-0.1.5.dist-info/LICENSE
flask_lambda_support-0.1.5.dist-info/METADATA
flask_lambda_support-0.1.5.dist-info/WHEEL
flask_lambda_support-0.1.5.dist-info/top_level.txt
flask_lambda_support-0.1.5.dist-info/RECORD
