Metadata-Version: 2.1
Name: flask-lambda-support
Version: 0.1.5
Summary: Python 3.6+ module to make Flask compatible with AWS Lambda
Home-page: https://github.com/becloudway/flask-lambda
Author: Jochen Van de Velde
Author-email: jochen.vandevelde@cloudway.be
License: Apache License, Version 2.0
Keywords: flask aws amazon lambda
Platform: UNKNOWN
Classifier: Development Status :: 5 - Production/Stable
Classifier: Programming Language :: Python
Classifier: Environment :: Console
Classifier: Operating System :: POSIX
Classifier: Programming Language :: Python :: 3.6
Classifier: Intended Audience :: Developers
Classifier: Natural Language :: English
Classifier: License :: OSI Approved :: Apache Software License
Requires-Dist: Flask (>=0.10)
